pydeltalake/__init__.py
pydeltalake/lib.py
pydeltalake-0.0.0.dist-info/METADATA
pydeltalake-0.0.0.dist-info/WHEEL
pydeltalake-0.0.0.dist-info/top_level.txt
pydeltalake-0.0.0.dist-info/RECORD
