Metadata-Version: 2.1
Name: pydeltalake
Version: 0.0.0
Summary: A Delta Lake implementation for Python
Home-page: https://github.com/pypa/sampleproject
Author: Marcio Parise Boufleur
Author-email: boufleur@gmail.com
License: UNKNOWN
Platform: UNKNOWN
Classifier: Programming Language :: Python :: 3
Classifier: License :: OSI Approved :: MIT License
Classifier: Operating System :: OS Independent
Requires-Python: >=3.6
